bog/__init__.py
bog/scraper.py
bank_of_ghana_fx_rates-1.0.1.dist-info/LICENSE
bank_of_ghana_fx_rates-1.0.1.dist-info/METADATA
bank_of_ghana_fx_rates-1.0.1.dist-info/WHEEL
bank_of_ghana_fx_rates-1.0.1.dist-info/top_level.txt
bank_of_ghana_fx_rates-1.0.1.dist-info/RECORD
