Metadata-Version: 2.1
Name: bank-of-ghana-fx-rates
Version: 1.0.1
Summary: A python client library used to extract the exchange rates of Bank of Ghana into CSV
Home-page: https://github.com/donwany/bank-of-ghana-fx-rates.git
Author: Theophilus Siameh
Author-email: theodondre@gmail.com
License: UNKNOWN
Keywords: Bank of Ghana,Ghana,Ghana API,Bank of Ghana Exchange Rates,government of Ghana,finance,APIs
Platform: UNKNOWN
Classifier: Development Status :: 3 - Alpha
Classifier: Intended Audience :: Developers
Classifier: Intended Audience :: Science/Research
Classifier: Intended Audience :: Financial and Insurance Industry
Classifier: License :: OSI Approved :: MIT License
Classifier: Natural Language :: English
Classifier: Operating System :: OS Independent
Classifier: Programming Language :: Python
Classifier: Programming Language :: Python :: 3
Classifier: Programming Language :: Python :: 3.8
Classifier: Topic :: Database
Classifier: Topic :: Education
Classifier: Topic :: Office/Business
Requires-Python: >=3.5
License-File: LICENSE
Requires-Dist: requests
Requires-Dist: pandas
Requires-Dist: urllib3
Requires-Dist: bs4
Requires-Dist: lxml
Requires-Dist: click
Requires-Dist: pyfiglet
